{
  "subjects": [
    {
      "name": "Photography",
      "career": "Design media",
      "credits": "3",
      "image": "https://picsum.photos/250/150",
      "rating": "4"
    },
    {
      "name": "Digital Design",
      "career": "Design media",
      "credits": "4",
      "image": "https://picsum.photos/250/150",
      "rating": "5"
    },
    {
      "name": "Two-dimensional",
      "career": "Design media",
      "credits": "3",
      "image": "https://picsum.photos/250/150",
      "rating": "4"
    },
    {
      "name": "Motion Graphics",
      "career": "Design media",
      "credits": "4",
      "image": "https://picsum.photos/250/150",
      "rating": "5"
    },
    {
      "name": "Web Design",
      "career": "Design media",
      "credits": "3",
      "image": "https://picsum.photos/250/150",
      "rating": "5"
    },
    {
      "name": "Criminal Law",
      "career": "Law",
      "credits": "4",
      "image": "https://picsum.photos/250/150",
      "rating": "4"
    },
    {
      "name": "Human Anatomy",
      "career": "Medicine",
      "credits": "5",
      "image": "https://picsum.photos/250/150",
      "rating": "5"
    },
    {
      "name": "Digital Strategies",
      "career": "Int. Mktg & Adv.",
      "credits": "3",
      "image": "https://picsum.photos/250/150",
      "rating": "4"
    },
    {
      "name": "Clinical Psychology",
      "career": "Psychology",
      "credits": "4",
      "image": "https://picsum.photos/250/150",
      "rating": "5"
    },
    {
      "name": "Organic Chemistry",
      "career": "Chemistry",
      "credits": "4",
      "image": "https://picsum.photos/250/150",
      "rating": "5"
    },
    {
      "name": "Algorithms",
      "career": "Systems Engineering",
      "credits": "4",
      "image": "https://picsum.photos/250/150",
      "rating": "4"
    },
    {
      "name": "Industrial Processes",
      "career": "Industrial Engineering",
      "credits": "4",
      "image": "https://picsum.photos/250/150",
      "rating": "4"
    },
    {
      "name": "Music Theory",
      "career": "Music",
      "credits": "3",
      "image": "https://picsum.photos/250/150",
      "rating": "4"
    },
    {
      "name": "Corporate",
      "career": "Finance",
      "credits": "4",
      "image": "https://picsum.photos/250/150",
      "rating": "5"
    },
    {
      "name": "Genetic Eng.",
      "career": "Biochemical Engineering",
      "credits": "4",
      "image": "https://picsum.photos/250/150",
      "rating": "5"
    },
    {
      "name": "Data Structures",
      "career": "Computer Science",
      "credits": "4",
      "image": "https://picsum.photos/250/150",
      "rating": "5"
    },
    {
      "name": "Machine Learning",
      "career": "Artificial Intelligence",
      "credits": "4",
      "image": "https://picsum.photos/250/150",
      "rating": "5"
    },
    {
      "name": "Environmental Law",
      "career": "Law",
      "credits": "3",
      "image": "https://picsum.photos/250/150",
      "rating": "4"
    },
    {
      "name": "Neuroscience",
      "career": "Medicine",
      "credits": "4",
      "image": "https://picsum.photos/250/150",
      "rating": "5"
    },
    {
      "name": "Microeconomics",
      "career": "Int. Mktg & Adv.",
      "credits": "3",
      "image": "https://picsum.photos/250/150",
      "rating": "4"
    },
    {
      "name": "Child Psychology",
      "career": "Psychology",
      "credits": "3",
      "image": "https://picsum.photos/250/150",
      "rating": "4"
    },
    {
      "name": "Physical Chemistry",
      "career": "Chemistry",
      "credits": "4",
      "image": "https://picsum.photos/250/150",
      "rating": "5"
    },
    {
      "name": "Cloud Computing",
      "career": "Systems Engineering",
      "credits": "4",
      "image": "https://picsum.photos/250/150",
      "rating": "5"
    },
    {
      "name": "Quality Control",
      "career": "Industrial Engineering",
      "credits": "3",
      "image": "https://picsum.photos/250/150",
      "rating": "4"
    }
  ]
}
